exchange2org/__init__.py
exchange2org/exchange2orgconfig-TEMPLATE.py
exchange2org-2018.05.21.01.dist-info/DESCRIPTION.rst
exchange2org-2018.05.21.01.dist-info/METADATA
exchange2org-2018.05.21.01.dist-info/RECORD
exchange2org-2018.05.21.01.dist-info/WHEEL
exchange2org-2018.05.21.01.dist-info/entry_points.txt
exchange2org-2018.05.21.01.dist-info/metadata.json
exchange2org-2018.05.21.01.dist-info/top_level.txt
