Metadata-Version: 2.0
Name: exchange2org
Version: 2018.05.21.01
Summary: Extracting data from Microsoft Exchange into Org-mode format
Home-page: https://github.com/novoid/exchange2org
Author: Karl Voit
Author-email: tools@Karl-Voit.at
License: UNKNOWN
Download-URL: https://github.com/novoid/exchange2org/zipball/master
Keywords: calendar,exchange,orgmode
Platform: UNKNOWN
Classifier: Programming Language :: Python :: 3 :: Only
Classifier: Development Status :: 5 - Production/Stable
Classifier: Environment :: Console
Classifier: Intended Audience :: End Users/Desktop
Classifier: License :: OSI Approved :: GNU General Public License (GPL)
Classifier: Operating System :: OS Independent
Requires-Dist: exchangelib
